cscribe/README.md
cscribe/__init__.py
cscribe/conversion.py
cscribe/mbtr.py
cscribe/sf.py
cscribe/soap.py
cscribe-0.3.1.dist-info/LICENSE
cscribe-0.3.1.dist-info/WHEEL
cscribe-0.3.1.dist-info/METADATA
cscribe-0.3.1.dist-info/RECORD
